makcu/README.md
makcu/__init__.py
makcu/__main__.py
makcu/conftest.py
makcu/connection.py
makcu/controller.py
makcu/enums.py
makcu/errors.py
makcu/makcu.pyi
makcu/mouse.py
makcu/py.typed
makcu/test_suite.py
makcu-2.3.1.dist-info/licenses/LICENSE
makcu-2.3.1.dist-info/METADATA
makcu-2.3.1.dist-info/WHEEL
makcu-2.3.1.dist-info/top_level.txt
makcu-2.3.1.dist-info/RECORD
